string_analysis/__init__.py
string_analysis/string_analysis.py
gabriel_take_string-0.0.3.dist-info/METADATA
gabriel_take_string-0.0.3.dist-info/WHEEL
gabriel_take_string-0.0.3.dist-info/top_level.txt
gabriel_take_string-0.0.3.dist-info/RECORD
